{
  "$schema": "https://raw.githubusercontent.com/badlogic/pi-mono/main/packages/coding-agent/src/modes/interactive/theme/theme-schema.json",
  "name": "tokyonight",
  "vars": {
    "bg": "#011628",
    "bgDark": "#011423",
    "bgPopup": "#011423",
    "bgHighlight": "#143652",
    "bgCustom": "#0A64AC",
    "bgSuccess": "#164846",
    "bgError": "#703438",
    "blue": "#7aa2f7",
    "cyan": "#7dcfff",
    "teal": "#73daca",
    "green": "#9ece6a",
    "red": "#f7768e",
    "redStrong": "#db4b4b",
    "yellow": "#e0af68",
    "orange": "#ff9e64",
    "purple": "#bb9af7",
    "comment": "#565f89",
    "muted": "#787c99",
    "dim": "#545c7e",
    "border": "#547998",
    "borderMuted": "#363b54"
  },
  "colors": {
    "accent": "blue",
    "border": "border",
    "borderAccent": "cyan",
    "borderMuted": "borderMuted",
    "success": "green",
    "error": "red",
    "warning": "yellow",
    "muted": "muted",
    "dim": "dim",
    "text": "#CBE0F0",
    "thinkingText": "muted",
    "selectedBg": "bgHighlight",
    "userMessageBg": "bgDark",
    "userMessageText": "#CBE0F0",
    "customMessageBg": "bgCustom",
    "customMessageText": "#CBE0F0",
    "customMessageLabel": "purple",
    "toolPendingBg": "bgPopup",
    "toolSuccessBg": "bgSuccess",
    "toolErrorBg": "bgError",
    "toolTitle": "#CBE0F0",
    "toolOutput": "muted",
    "mdHeading": "yellow",
    "mdLink": "blue",
    "mdLinkUrl": "muted",
    "mdCode": "cyan",
    "mdCodeBlock": "green",
    "mdCodeBlockBorder": "borderMuted",
    "mdQuote": "muted",
    "mdQuoteBorder": "borderMuted",
    "mdHr": "borderMuted",
    "mdListBullet": "teal",
    "toolDiffAdded": "green",
    "toolDiffRemoved": "redStrong",
    "toolDiffContext": "muted",
    "syntaxComment": "comment",
    "syntaxKeyword": "purple",
    "syntaxFunction": "blue",
    "syntaxVariable": "#c0caf5",
    "syntaxString": "green",
    "syntaxNumber": "orange",
    "syntaxType": "teal",
    "syntaxOperator": "cyan",
    "syntaxPunctuation": "muted",
    "thinkingOff": "borderMuted",
    "thinkingMinimal": "muted",
    "thinkingLow": "blue",
    "thinkingMedium": "cyan",
    "thinkingHigh": "purple",
    "thinkingXhigh": "red",
    "bashMode": "green"
  },
  "export": {
    "pageBg": "bg",
    "cardBg": "bgDark",
    "infoBg": "#1a1b26"
  }
}

